loguru_logger_lite/__init__.py
loguru_logger_lite/logger.py
loguru_logger_lite-0.0.9.dist-info/licenses/LICENSE.md
loguru_logger_lite-0.0.9.dist-info/METADATA
loguru_logger_lite-0.0.9.dist-info/WHEEL
loguru_logger_lite-0.0.9.dist-info/top_level.txt
loguru_logger_lite-0.0.9.dist-info/RECORD
