Metadata-Version: 2.4
Name: loguru_logger_lite
Version: 0.0.9
Summary: Simple loguru_logger_lite built on top of loguru to make a quick setup for basic logging
Home-page: https://github.com/doctor3030/loguru-logger-lite
Author: Dmitry Amanov
Author-email: 
License: MIT
Classifier: License :: OSI Approved :: MIT License
Classifier: Programming Language :: Python :: 3
Requires-Python: >=3.8
License-File: LICENSE.md
Requires-Dist: pydantic~=2.11.0
Requires-Dist: loguru~=0.7.3
Requires-Dist: kafka-python~=2.0.6
Dynamic: author
Dynamic: classifier
Dynamic: description
Dynamic: description-content-type
Dynamic: home-page
Dynamic: license
Dynamic: license-file
Dynamic: requires-dist
Dynamic: requires-python
Dynamic: summary
